ccp.py
python_ccp-1.3.data/scripts/ccp.py
python_ccp-1.3.dist-info/DESCRIPTION.rst
python_ccp-1.3.dist-info/METADATA
python_ccp-1.3.dist-info/RECORD
python_ccp-1.3.dist-info/WHEEL
python_ccp-1.3.dist-info/entry_points.txt
python_ccp-1.3.dist-info/metadata.json
python_ccp-1.3.dist-info/top_level.txt
