Metadata-Version: 2.0
Name: python-ccp
Version: 1.3
Summary: copy paste program with clip-server use stdin and stdout
Home-page: https://github.com/bongtrop/ccp
Author: Pongsakorn Sommalai
Author-email: bongtrop@gmail.com
License: MIT
Keywords: copy paste tool
Platform: UNKNOWN
Requires-Dist: requests
Requires-Dist: docopt-dispatch
Requires-Dist: pycrypto
